api2pydantic/__init__.py
api2pydantic/__main__.py
api2pydantic/analyzer.py
api2pydantic/cli.py
api2pydantic/fetcher.py
api2pydantic/generator.py
api2pydantic/utils.py
api2pydantic-0.1.0.dist-info/licenses/LICENSE
tests/__init__.py
tests/test_analyzer.py
api2pydantic-0.1.0.dist-info/METADATA
api2pydantic-0.1.0.dist-info/WHEEL
api2pydantic-0.1.0.dist-info/entry_points.txt
api2pydantic-0.1.0.dist-info/top_level.txt
api2pydantic-0.1.0.dist-info/RECORD
