Metadata-Version: 2.4
Name: api2pydantic
Version: 0.1.0
Summary: Automatically generate Pydantic models from API responses
Home-page: https://github.com/codedev1992/api2pydantic
Author: Sornalingam
Author-email: Sornalingam <devcode1992@gmail.com>
License: MIT
Project-URL: Homepage, https://github.com/codedev1992/api2pydantic
Project-URL: Documentation, https://github.com/codedev1992/api2pydantic#readme
Project-URL: Repository, https://github.com/codedev1992/api2pydantic
Project-URL: Bug Tracker, https://github.com/codedev1992/api2pydantic/issues
Keywords: pydantic,api,json,schema,generator,code-generation
Classifier: Development Status :: 4 - Beta
Classifier: Intended Audience :: Developers
Classifier: Topic :: Software Development :: Code Generators
Classifier: License :: OSI Approved :: MIT License
Classifier: Programming Language :: Python :: 3
Classifier: Programming Language :: Python :: 3.8
Classifier: Programming Language :: Python :: 3.9
Classifier: Programming Language :: Python :: 3.10
Classifier: Programming Language :: Python :: 3.11
Classifier: Programming Language :: Python :: 3.12
Requires-Python: >=3.8
License-File: LICENSE
Requires-Dist: pydantic>=2.0.0
Requires-Dist: requests>=2.28.0
Requires-Dist: click>=8.0.0
Provides-Extra: dev
Requires-Dist: pytest>=7.0.0; extra == "dev"
Requires-Dist: pytest-cov>=4.0.0; extra == "dev"
Requires-Dist: flake8>=6.0.0; extra == "dev"
Requires-Dist: black>=23.0.0; extra == "dev"
Requires-Dist: mypy>=1.0.0; extra == "dev"
Dynamic: author
Dynamic: home-page
Dynamic: license-file
Dynamic: requires-python
